pytabular/__init__.py
pytabular/best_practice_analyzer.py
pytabular/column.py
pytabular/culture.py
pytabular/document.py
pytabular/logic_utils.py
pytabular/measure.py
pytabular/object.py
pytabular/partition.py
pytabular/pbi_helper.py
pytabular/pytabular.py
pytabular/query.py
pytabular/refresh.py
pytabular/relationship.py
pytabular/table.py
pytabular/tabular_editor.py
pytabular/tabular_tracing.py
pytabular/tmdl.py
pytabular/dll/Microsoft.AnalysisServices.AdomdClient.dll
pytabular/dll/Microsoft.AnalysisServices.Core.dll
pytabular/dll/Microsoft.AnalysisServices.Tabular.Json.dll
pytabular/dll/Microsoft.AnalysisServices.Tabular.dll
pytabular/dll/Microsoft.AnalysisServices.dll
python_tabular-0.5.6.dist-info/licenses/LICENSE.txt
python_tabular-0.5.6.dist-info/METADATA
python_tabular-0.5.6.dist-info/WHEEL
python_tabular-0.5.6.dist-info/top_level.txt
python_tabular-0.5.6.dist-info/RECORD
