Metadata-Version: 2.4
Name: python_tabular
Version: 0.5.6
Summary: Connect to your tabular model and perform operations programmatically
Author-email: Curtis Stallings <curtisrstallings@gmail.com>
Project-URL: Homepage, https://github.com/Curts0/PyTabular
Project-URL: Bug Tracker, https://github.com/Curts0/PyTabular/issues
Classifier: Programming Language :: Python :: 3.8
Classifier: Programming Language :: Python :: 3.9
Classifier: Programming Language :: Python :: 3.10
Classifier: Programming Language :: Python :: 3.11
Classifier: Programming Language :: Python :: 3.12
Classifier: Programming Language :: Python :: 3.13
Classifier: Development Status :: 5 - Production/Stable
Classifier: Operating System :: Microsoft
Classifier: License :: OSI Approved :: MIT License
Requires-Python: >=3.8
License-File: LICENSE.txt
Requires-Dist: pythonnet>=3.0.3
Requires-Dist: clr-loader>=0.2.6
Requires-Dist: xmltodict==0.13.0
Requires-Dist: pandas>=1.4.3
Requires-Dist: requests>=2.28.1
Requires-Dist: rich>=12.5.1
Dynamic: license-file
